{
    "Productos": "Productos",
    "Medicamentos": "Medicamentos",
    "CuidadoNatural": "Cuidado Natural",
    "Herbolario": "Herbolario",
    "Ortopedia": "Ortopedia",
    "Contacto": "Contacto",
    "Todos_los_productos": "Todos los productos",
    "Siguenos": "Síguenos",
    "Todos_los_derechos_reservados": "Todos los derechos reservados",
    "Todos_los_productos_incluyen_IVA": "Todos los productos incluyen IVA",
    "Politica_Privacidad": "Política de Privacidad",
    "Condiciones_Uso": "Condiciones de Uso",
    "Condiciones_Contratacion": "Condiciones de Contratación",
    "Politica_Cookies": "Política de Cookies",
    "descripcionAceiteCannabis":"JB Oil 25% es un aceite rico en CBD de la nueva línea JB OIL. En JB Oil 25% encontramos una alta concentración de CBD, posible gracias a métodos innovadores de extracción y dilución de la sustancia en los que solo se utilizan materias primas orgánicas excepcionales. Mediante disolventes supercríticos de CO2, se extrae el CBD aislado que luego se mezclará con aceite de coco MCT (obtenido en cambio mediante una extracción en frío) para obtener el producto final totalmente inodoro e incoloro. La combinación con aceite de coco le da un sabor delicado e interesante. De esta forma, Justbob, cuyo fin último es mantener altos estándares de calidad en cada uno de sus productos, consigue incluir en su catálogo un aceite potente y natural, cuyas beneficiosas propiedades están intactas. Nuestro práctico y versátil aceite JB Oil será capaz de brindarte una intensa sensación de placer para disfrutar de momentos de pura relajación.",
    "btn-anadir":"Agregar al Carrito",
    "ModoEnvio":"Modo de Envio",
    "Recogida_Tienda":"Recogida en Tienda",
    "Envio24":"Envio 24h",
    "Envio48":"Envio 48h/72h",
    "direccionEntrega": "Dirección de entrega",
    "NombreApellido": "Nombre y Apellidos:",
    "direccionCasa": "Dirección:",
    "CodigoPostal": "Código Postal:",
    "Ciudad": "Ciudad:",
    "Provincia": "Provincia:",
    "Pais": "País:",
    "GuardarDatos": "Guardar Datos",
    "Contrareembolso": "Contrareembolso",
    "PayPal": "PayPal",
    "Transferencia": "Transferencia",
    "NumeroCuenta": "Número de cuenta: IBAN 134267893434561645878",
    "ResumenPedido": "Resumen del pedido",
    "Subtotal": "Subtotal",
    "GastosEnvio": "Gastos de envío",
    "RevisarCarrito": "Revisar carrito",
    "Continuar": "Continuar",
    "CompraRealizada": "Compra realizada, ¡muchas gracias!",
    "Seguir_comprando": "Seguir comprando",
    "Carrito": "Carrito",
    "Tu_carrito_tiene_hambre": "Tu carrito tiene hambre",
    "Vaciar_Carrito": "Vaciar carrito",
    "Total": "Total",
    "Pagar_Ahora": "Pagar ahora",
    "Muchas_Gracias": "Muchas gracias por la compra, disfruta de tu cuidado natural"
}
